gretel_trainer/__init__.py
gretel_trainer/models.py
gretel_trainer/runner.py
gretel_trainer/strategy.py
gretel_trainer/trainer.py
gretel_trainer/version.py
gretel_trainer/benchmark/__init__.py
gretel_trainer/benchmark/core.py
gretel_trainer/benchmark/entrypoints.py
gretel_trainer/benchmark/executor.py
gretel_trainer/benchmark/job_spec.py
gretel_trainer/benchmark/log.py
gretel_trainer/benchmark/sdk_extras.py
gretel_trainer/benchmark/session.py
gretel_trainer/benchmark/custom/datasets.py
gretel_trainer/benchmark/custom/models.py
gretel_trainer/benchmark/custom/strategy.py
gretel_trainer/benchmark/gretel/datasets.py
gretel_trainer/benchmark/gretel/datasets_backwards_compatibility.py
gretel_trainer/benchmark/gretel/models.py
gretel_trainer/benchmark/gretel/strategy_sdk.py
gretel_trainer/benchmark/gretel/strategy_trainer.py
gretel_trainer/relational/__init__.py
gretel_trainer/relational/ancestry.py
gretel_trainer/relational/backup.py
gretel_trainer/relational/connectors.py
gretel_trainer/relational/core.py
gretel_trainer/relational/extractor.py
gretel_trainer/relational/json.py
gretel_trainer/relational/log.py
gretel_trainer/relational/model_config.py
gretel_trainer/relational/multi_table.py
gretel_trainer/relational/output_handler.py
gretel_trainer/relational/sdk_extras.py
gretel_trainer/relational/table_evaluation.py
gretel_trainer/relational/task_runner.py
gretel_trainer/relational/workflow_state.py
gretel_trainer/relational/report/figures.py
gretel_trainer/relational/report/key_highlight.js
gretel_trainer/relational/report/report.css
gretel_trainer/relational/report/report.py
gretel_trainer/relational/report/report_privacy_protection.css
gretel_trainer/relational/report/report_synthetic_quality.css
gretel_trainer/relational/report/report_template.html
gretel_trainer/relational/strategies/ancestral.py
gretel_trainer/relational/strategies/common.py
gretel_trainer/relational/strategies/independent.py
gretel_trainer/relational/tasks/classify.py
gretel_trainer-0.11.4.dist-info/LICENSE
gretel_trainer-0.11.4.dist-info/METADATA
gretel_trainer-0.11.4.dist-info/WHEEL
gretel_trainer-0.11.4.dist-info/top_level.txt
gretel_trainer-0.11.4.dist-info/RECORD
